kpireport_sendgrid/__init__.py
kpireport_sendgrid/output.py
kpireport_sendgrid-0.0.1.dist-info/METADATA
kpireport_sendgrid-0.0.1.dist-info/WHEEL
kpireport_sendgrid-0.0.1.dist-info/entry_points.txt
kpireport_sendgrid-0.0.1.dist-info/top_level.txt
kpireport_sendgrid-0.0.1.dist-info/RECORD
